modular_pipeline-0.2.6.dist-info/licenses/LICENSE.txt
pipeline/__init__.py
pipeline/scripts/__init__.py
pipeline/scripts/pipeline.py
pipeline/scripts/pipeline_utils.py
modular_pipeline-0.2.6.dist-info/METADATA
modular_pipeline-0.2.6.dist-info/WHEEL
modular_pipeline-0.2.6.dist-info/top_level.txt
modular_pipeline-0.2.6.dist-info/RECORD
